AUTHORS.rst
LICENSE
MANIFEST.in
README.md
setup.py
admin_shortcuts/__init__.py
admin_shortcuts/templates/admin/index.html
admin_shortcuts/templates/admin_shortcuts/base.css
admin_shortcuts/templates/admin_shortcuts/base.html
admin_shortcuts/templates/admin_shortcuts/shortcut.html
admin_shortcuts/templates/admin_shortcuts/style.css
admin_shortcuts/templatetags/__init__.py
admin_shortcuts/templatetags/admin_shortcuts_tags.py
django_admin_shortcuts.egg-info/PKG-INFO
django_admin_shortcuts.egg-info/SOURCES.txt
django_admin_shortcuts.egg-info/dependency_links.txt
django_admin_shortcuts.egg-info/requires.txt
django_admin_shortcuts.egg-info/top_level.txt