Metadata-Version: 2.1
Name: django-admin-shortcuts
Version: 3.0.1
Summary: Add simple and pretty shortcuts to the django admin homepage.
Home-page: https://github.com/alesdotio/django-admin-shortcuts
Download-URL: https://github.com/alesdotio/django-admin-shortcuts/tarball/3.0.1
Author: Ales Kocjancic
Author-email: alesdotio@gmail.com
License: BSD
Classifier: Development Status :: 3 - Alpha
Classifier: Intended Audience :: Developers
Classifier: Programming Language :: Python :: 3
License-File: LICENSE
License-File: AUTHORS.rst
